{
  "Web Development": [
    {
      "id": 1,
      "name": "Sheriyans Coding School",
      "category": "Web Development",
      "level": "Beginner",
      "type": "Project-Based",
      "cost": "Free & Paid",
      "language": "English & Hindi",
      "duration": "3-12 Months",
      "bestFor": "Students who prefer practical, project-based learning with an active community",
      "description": "Offers practical web development courses focused on building real-world projects and improving development skills.",
      "link": "https://www.sheriyans.com/"
    },
    {
      "id": 2,
      "name": "freeCodeCamp",
      "category": "Web Development",
      "level": "Beginner",
      "type": "Interactive",
      "cost": "Free",
      "language": "English",
      "duration": "6-12 Months",
      "bestFor": "Beginners who want a structured curriculum with coding exercises and certifications",
      "description": "A free learning platform offering interactive lessons, coding challenges, projects, and certifications.",
      "link": "https://www.freecodecamp.org/"
    },
    {
      "id": 3,
      "name": "The Odin Project",
      "category": "Web Development",
      "level": "Intermediate",
      "type": "Project-Based",
      "cost": "Free",
      "language": "English",
      "duration": "6-12 Months",
      "bestFor": "Learners who want to build real-world projects and become full-stack developers",
      "description": "A comprehensive full-stack web development curriculum focused on hands-on projects and modern development workflows.",
      "link": "https://www.theodinproject.com/"
    },
    {
      "id": 4,
      "name": "Full Stack Open",
      "category": "Web Development",
      "level": "Advanced",
      "type": "Project-Based",
      "cost": "Free",
      "language": "English",
      "duration": "3-6 Months",
      "bestFor": "Developers who already know the basics and want to master modern full-stack development",
      "description": "An advanced course covering React, Node.js, databases, testing, and deployment.",
      "link": "https://fullstackopen.com/"
    },
    {
      "id": 5,
      "name": "MDN Web Docs",
      "category": "Web Development",
      "level": "Expert",
      "type": "Documentation",
      "cost": "Free",
      "language": "English",
      "duration": "Self-Paced",
      "bestFor": "Developers who need in-depth documentation and professional reference material",
      "description": "The official documentation for HTML, CSS, JavaScript, Web APIs, and modern web technologies.",
      "link": "https://developer.mozilla.org"
    }
  ],
  "AI/ML": [
    {
      "id": 1,
      "name": "Google Machine Learning Crash Course",
      "category": "AI/ML",
      "level": "Beginner",
      "type": "Interactive",
      "cost": "Free",
      "language": "English",
      "duration": "2-4 Months",
      "bestFor": "Beginners who want to learn machine learning fundamentals",
      "description": "A beginner-friendly course covering core machine learning concepts with interactive exercises and real-world examples.",
      "link": "https://developers.google.com/machine-learning/crash-course"
    },
    {
      "id": 2,
      "name": "Kaggle Learn",
      "category": "AI/ML",
      "level": "Beginner",
      "type": "Interactive",
      "cost": "Free",
      "language": "English",
      "duration": "1-3 Months",
      "bestFor": "Learners who enjoy hands-on coding and datasets",
      "description": "Short practical courses covering Python, machine learning, data visualization, and deep learning.",
      "link": "https://www.kaggle.com/learn"
    },
    {
      "id": 3,
      "name": "Machine Learning Specialization by Andrew Ng",
      "category": "AI/ML",
      "level": "Intermediate",
      "type": "Video Course",
      "cost": "Free & Paid",
      "language": "English",
      "duration": "3-6 Months",
      "bestFor": "Students who want a strong theoretical and practical foundation in machine learning",
      "description": "A comprehensive specialization covering supervised learning, neural networks, and best practices.",
      "link": "https://www.coursera.org/specializations/machine-learning-introduction"
    },
    {
      "id": 4,
      "name": "fast.ai",
      "category": "AI/ML",
      "level": "Advanced",
      "type": "Project-Based",
      "cost": "Free",
      "language": "English",
      "duration": "3-6 Months",
      "bestFor": "Developers who want to build deep learning applications",
      "description": "A practical deep learning course focused on building real-world AI applications using PyTorch.",
      "link": "https://course.fast.ai"
    },
    {
      "id": 5,
      "name": "Papers with Code",
      "category": "AI/ML",
      "level": "Expert",
      "type": "Research",
      "cost": "Free",
      "language": "English",
      "duration": "Self-Paced",
      "bestFor": "Experienced learners exploring state-of-the-art AI research",
      "description": "A platform linking cutting-edge AI research papers with code implementations, benchmarks, and datasets.",
      "link": "https://paperswithcode.com"
    }
  ],
  "Cybersecurity": [
    {
      "id": 1,
      "name": "TryHackMe",
      "category": "Cybersecurity",
      "level": "Beginner",
      "type": "Interactive",
      "cost": "Free & Paid",
      "language": "English",
      "duration": "2-6 Months",
      "bestFor": "Beginners who want hands-on cybersecurity training",
      "description": "An interactive platform teaching cybersecurity through guided labs, rooms, and real-world scenarios.",
      "link": "https://tryhackme.com"
    },
    {
      "id": 2,
      "name": "OverTheWire",
      "category": "Cybersecurity",
      "level": "Beginner",
      "type": "Hands-On",
      "cost": "Free",
      "language": "English",
      "duration": "1-3 Months",
      "bestFor": "Students who want to learn Linux and security fundamentals through challenges",
      "description": "A collection of wargames designed to teach Linux, networking, and security concepts step by step.",
      "link": "https://overthewire.org"
    },
    {
      "id": 3,
      "name": "PortSwigger Web Security Academy",
      "category": "Cybersecurity",
      "level": "Intermediate",
      "type": "Interactive",
      "cost": "Free",
      "language": "English",
      "duration": "3-6 Months",
      "bestFor": "Learners interested in web application security and penetration testing",
      "description": "Free labs and tutorials covering web vulnerabilities like SQL injection, XSS, CSRF, and authentication flaws.",
      "link": "https://portswigger.net/web-security"
    },
    {
      "id": 4,
      "name": "Hack The Box",
      "category": "Cybersecurity",
      "level": "Advanced",
      "type": "Hands-On",
      "cost": "Free & Paid",
      "language": "English",
      "duration": "6-12 Months",
      "bestFor": "Users who want realistic penetration testing and ethical hacking practice",
      "description": "A platform featuring vulnerable machines and labs that simulate real-world cybersecurity challenges.",
      "link": "https://www.hackthebox.com"
    },
    {
      "id": 5,
      "name": "Offensive Security Learning Library (OSCC/OSCP)",
      "category": "Cybersecurity",
      "level": "Expert",
      "type": "Professional Training",
      "cost": "Paid",
      "language": "English",
      "duration": "3-12 Months",
      "bestFor": "Professionals preparing for advanced penetration testing certifications",
      "description": "Industry-recognized training focused on ethical hacking, penetration testing, and advanced offensive security techniques.",
      "link": "https://www.offsec.com"
    }
  ],
  "DSA": [
    {
      "id": 1,
      "name": "Striver's A2Z DSA Course",
      "category": "DSA",
      "level": "Beginner",
      "type": "Structured Course",
      "cost": "Free",
      "language": "English",
      "duration": "3-6 Months",
      "bestFor": "Beginners preparing for coding interviews",
      "description": "A complete roadmap covering Data Structures and Algorithms from basic to advanced with practice problems.",
      "link": "https://takeuforward.org"
    },
    {
      "id": 2,
      "name": "GeeksforGeeks DSA",
      "category": "DSA",
      "level": "Beginner",
      "type": "Articles & Practice",
      "cost": "Free & Paid",
      "language": "English",
      "duration": "3-6 Months",
      "bestFor": "Students who prefer detailed explanations and extensive practice",
      "description": "Comprehensive tutorials, coding problems, and interview preparation resources for Data Structures and Algorithms.",
      "link": "https://www.geeksforgeeks.org"
    },
    {
      "id": 3,
      "name": "NeetCode",
      "category": "DSA",
      "level": "Intermediate",
      "type": "Video & Practice",
      "cost": "Free & Paid",
      "language": "English",
      "duration": "2-4 Months",
      "bestFor": "Learners preparing for technical interviews with curated coding problems",
      "description": "A structured roadmap featuring carefully selected coding interview questions with video explanations.",
      "link": "https://neetcode.io"
    },
    {
      "id": 4,
      "name": "LeetCode",
      "category": "DSA",
      "level": "Advanced",
      "type": "Coding Practice",
      "cost": "Free & Paid",
      "language": "English",
      "duration": "Self-Paced",
      "bestFor": "Developers preparing for coding interviews at top tech companies",
      "description": "A leading platform for practicing coding problems across algorithms, data structures, and system design.",
      "link": "https://leetcode.com"
    },
    {
      "id": 5,
      "name": "Codeforces",
      "category": "DSA",
      "level": "Expert",
      "type": "Competitive Programming",
      "cost": "Free",
      "language": "English",
      "duration": "Self-Paced",
      "bestFor": "Advanced programmers aiming to master algorithms through competitive programming",
      "description": "A competitive programming platform featuring contests, problem sets, and an active global community.",
      "link": "https://codeforces.com"
    }
  ]
}